dompower/__init__.py
dompower/__main__.py
dompower/auth.py
dompower/client.py
dompower/const.py
dompower/exceptions.py
dompower/gigya_auth.py
dompower/models.py
dompower/py.typed
dompower-0.1.4.dist-info/METADATA
dompower-0.1.4.dist-info/WHEEL
dompower-0.1.4.dist-info/entry_points.txt
dompower-0.1.4.dist-info/RECORD
