Metadata-Version: 2.4
Name: dompower
Version: 0.1.4
Summary: Async Python client for Dominion Energy API
Project-URL: Homepage, https://github.com/YeomansIII/dompower
Project-URL: Repository, https://github.com/YeomansIII/dompower
Author: Jason Yeomans
License: MIT
Keywords: api,async,dominion,energy,home-assistant,utility
Classifier: Development Status :: 3 - Alpha
Classifier: Intended Audience :: Developers
Classifier: License :: OSI Approved :: MIT License
Classifier: Programming Language :: Python :: 3
Classifier: Programming Language :: Python :: 3.12
Classifier: Programming Language :: Python :: 3.13
Classifier: Topic :: Home Automation
Classifier: Typing :: Typed
Requires-Python: >=3.12
Requires-Dist: aiohttp>=3.10.0
Requires-Dist: openpyxl>=3.1.5
Provides-Extra: dev
Requires-Dist: aresponses>=3.0.0; extra == 'dev'
Requires-Dist: mypy>=1.11.0; extra == 'dev'
Requires-Dist: pre-commit>=4.0.0; extra == 'dev'
Requires-Dist: pytest-aiohttp>=1.0.5; extra == 'dev'
Requires-Dist: pytest-asyncio>=0.24.0; extra == 'dev'
Requires-Dist: pytest>=8.3.0; extra == 'dev'
Requires-Dist: ruff>=0.6.0; extra == 'dev'
